mailValidator/__init__.py
mailValidator/email_utils.py
mailValidator/example_usage.py
mailValidator/terminalScript/__init__.py
mailValidator/terminalScript/argument_parser.py
mailValidator/terminalScript/config_data.py
mailValidator/terminalScript/file_writer.py
mailValidator/terminalScript/progress.py
mailValidator/terminalScript/script_console.py
mailValidator/utils/__init__.py
mailValidator/utils/catch_all_utils.py
mailValidator/utils/config.py
mailValidator/utils/dns_utils.py
mailValidator/utils/logging_utils.py
mailValidator/utils/smtp_utils.py
mailValidator-0.2.1.1.dist-info/LICENSE.txt
mailValidator-0.2.1.1.dist-info/METADATA
mailValidator-0.2.1.1.dist-info/WHEEL
mailValidator-0.2.1.1.dist-info/entry_points.txt
mailValidator-0.2.1.1.dist-info/top_level.txt
mailValidator-0.2.1.1.dist-info/RECORD
